p2e/HTMLReader.py
p2e/RTFReader.py
p2e/__init__.py
p2e/exportcsv.py
p2e/exportxlsx.py
p2e/main.py
p2e/utils.py
test_polyspace_report2excel-1.0.4.dist-info/LICENSE
test_polyspace_report2excel-1.0.4.dist-info/METADATA
test_polyspace_report2excel-1.0.4.dist-info/WHEEL
test_polyspace_report2excel-1.0.4.dist-info/entry_points.txt
test_polyspace_report2excel-1.0.4.dist-info/top_level.txt
test_polyspace_report2excel-1.0.4.dist-info/RECORD
