Metadata-Version: 2.1
Name: test-polyspace-report2excel
Version: 1.0.4
Summary: read a polyspace report and export misra or run-time results
Author-email: CAT Lab <L-lequal@cnes.fr>
Maintainer-email: CAT Lab <L-lequal@cnes.fr>
License: GNU GENERAL PUBLIC LICENSE
Project-URL: Homepage, https://github.com/cnescatlab/polyspace-report2excel
Project-URL: Bug Reports, https://github.com/cnescatlab/polyspace-report2excel/issues
Keywords: polyspace,report,excel,misra
Classifier: Development Status :: 5 - Production/Stable
Classifier: Intended Audience :: Developers
Classifier: Topic :: Software Development :: Quality Assurance
Classifier: License :: OSI Approved :: GNU General Public License v3 (GPLv3)
Classifier: Programming Language :: Python :: 3
Requires-Python: >=3
License-File: LICENSE
Requires-Dist: XlsxWriter
Requires-Dist: html2text
Requires-Dist: striprtf
